scikitty/__init__.py
scikitty/export/__init__.py
scikitty/metrics/__init__.py
scikitty/metrics/accuracy_score.py
scikitty/metrics/confusion_matrix.py
scikitty/metrics/f1_score.py
scikitty/metrics/precision_score.py
scikitty/metrics/recall_score.py
scikitty/model_selection/__init__.py
scikitty/model_selection/train_test_split.py
scikitty/models/DecisionStump.py
scikitty/models/DecisionTree.py
scikitty/models/LinearRegression.py
scikitty/models/LogisticRegression.py
scikitty/models/TreeBoosting.py
scikitty/models/__init__.py
scikitty/persist/TreePersistence.py
scikitty/persist/__init__.py
scikitty/view/TreeVisualizer.py
scikitty/view/__init__.py
scikitty-0.7.dist-info/METADATA
scikitty-0.7.dist-info/WHEEL
scikitty-0.7.dist-info/top_level.txt
scikitty-0.7.dist-info/RECORD
