Metadata-Version: 2.1
Name: scikitty
Version: 0.7
Summary: A package to create Decision Trees like Scikitlearn.
Home-page: https://github.com/JohnRojas222/SciKittyPackage/
Download-URL: https://github.com/JohnRojas222/SciKittyPackage/tarball/0.1
Author: John Rojas
Author-email: john.rojas.chinchilla@gmail.com
License: MIT
Keywords: scikitlearn,decision trees,metrics
Requires-Dist: setuptools (==68.0.0)
Requires-Dist: wheel (==0.38.4)
Requires-Dist: twine (==5.1.0)
Requires-Dist: pandas (==2.1.4)
Requires-Dist: numpy (==1.24.3)
Requires-Dist: scikit-image (==0.20.0)
Requires-Dist: scikit-learn (==1.3.0)
Requires-Dist: scikit-learn-intelex (==2024.4.0)
Requires-Dist: graphviz (==0.20.3)
